Fonte/registrador.v
module registrador(wr_enable,clock,entrada_reg,saida_reg);

input wr_enable;
input clock;
input [15:0] entrada_reg;
output reg [15:0] saida_reg;

always @(posedge clock)
begin
    if(wr_enable)
        saida_reg <= entrada_reg;
end

endmodule

Fonte/decodificador.v
module decodificador(
    input      [2:0] chave,
    output reg [7:0] saida
);

always @(chave) begin
    saida        = 8'h00;
    saida[chave] = 1'b1;
end

endmodule

Fonte/logica_de_controle.v
`include "decodificador.v"

module logica_de_controle(
    input            resetn,
    input      [1:0] counter,
    input      [8:0] iin,
    output reg [3:0] mux_select,
    output     [7:0] regs_enable,
    output     [1:0] alu_op_select,
    output           a_reg_enable,
    output           alu_reg_enable,
    output reg       clear
);

`define REP 3'b111
`define ADD 3'b000 
`define SUB 3'b001 
`define NAN 3'b010
`define LDI 3'b101
`define OUT 3'b100

`define ALU_OPERATION (opcode == `ADD || opcode == `SUB || opcode == `NAN)
`define IMM_SELECT      4'b1000 
`define ULA_OUT_SELECT  4'b1001 
`define NO_OUTPUT       4'b1111

reg  [2:0] opcode, rx, ry;
wire [7:0] regs_select;
decodificador decode(rx, regs_select);

//Habilita a escrita no registrador de entrada da ULA.
assign a_reg_enable   = (counter == 2'b01 && `ALU_OPERATION); 

//Habilita a escrita no regitrador de saída da ULA.
assign alu_reg_enable = (counter == 2'b10 && `ALU_OPERATION);

//Determina qual operação deve ser realizada pela ULA. ('11' é no_op).
assign alu_op_select  = (`ALU_OPERATION) ? opcode[1:0] : 2'b11;

//Cada elemento desse array de 8 bits é ligado ao campo 'wr_enable' de um dos
//8 registradores endereçáveis.
assign regs_enable    = (counter == 2'b11 && opcode != `OUT) ? regs_select : 8'h00;

always @(counter) 
begin
    case(counter)

    2'b00: mux_select <= `NO_OUTPUT;

    2'b01: begin
        opcode = iin[8:6];
        rx     = iin[5:3];
        ry     = iin[2:0];

        if(`ALU_OPERATION)
            mux_select <= {1'b0,rx};
    end

    2'b10: 
        if(`ALU_OPERATION)
            mux_select <= {1'b0,ry};

    2'b11: 
        case(opcode)
            `OUT:    mux_select <= {1'b0, rx};
            `REP:    mux_select <= {1'b0, ry};
            `LDI:    mux_select <= `IMM_SELECT;
            default: mux_select <= `ULA_OUT_SELECT;
        endcase

    endcase
end

always @(negedge resetn)
begin
    clear = 1'b1;
    clear = 1'b0;
end

endmodule

Fonte/multiplexador.v
module multiplexador (
    input  wire [3:0] select,
    input  wire [15:0] immediate,
    input  wire [15:0] r0, r1, r2, r3, r4, r5, r6, r7,
    input  wire [15:0] r,
    output reg  [15:0] saida
);
    always @(*)
    case (select)
        4'd0: saida = r0; 
        4'd1: saida = r1;
        4'd2: saida = r2;
        4'd3: saida = r3;
        4'd4: saida = r4;
        4'd5: saida = r5;
        4'd6: saida = r6;
        4'd7: saida = r7;
        4'd8: saida = immediate;
        4'd9: saida = r;
        default: saida = 16'dz;
    endcase
    
endmodule

/* Valores select -> Entrada selecionada

0000 -> r0
0001 -> r1
0010 -> r2
0011 -> r3
0100 -> r4
0101 -> r6
0110 -> r7
0111 -> r6
1000 -> Immediate
1001 -> r (Registrador ULA)
1010 -> *
1011 -> *
1100 -> *
1101 -> *
1110 -> *
1111 -> *
*/

Fonte/extensor.v
module extensor(
    input  [9:0] iin,
    output [15:0] imediato
);

assign imediato[9:0] = iin;
assign imediato[15:10] = {6{iin[9]}};

endmodule;

Fonte/contador.v
module contador(
    input clock,
    input clear,
    output reg [1:0] saida_cont);

always @(posedge clock)
begin
    if(clear)
        saida_cont <= 2'b00;
    else 
        saida_cont <= saida_cont + 2'b01;
end

endmodule

Fonte/processador.v
`include "registrador.v"
`include "logica_de_controle.v"
`include "multiplexador.v"
`include "contador.v"
`include "extensor.v"

module processador(
    input clock,
    input resetn,
    input  [15:0] iin,
    output [15:0] bus
);

wire [3:0] mux_select;
wire [7:0] regs_enable;
wire [1:0] alu_op_select;
wire [1:0] saida_contador;
wire [15:0] data_bus, imm, a_reg_out, alu_out;
wire [15:0] r0_out, r1_out, r2_out, r3_out, r4_out, r5_out, r6_out, r7_out;

contador cont(clock, clear, saida_contador);
extensor ext(iin[9:0], imm);
multiplexador mux(mux_select,imm,r0_out,r1_out,r2_out,r3_out,r4_out,r5_out,
    r6_out,r7_out,alu_out,data_bus);
logica_de_controle log_ctl(resetn, saida_contador, iin[15:7],
    mux_select, regs_enable, alu_op_select, a_reg_enable, alu_reg_enable,clear);

registrador r0(regs_enable[0],clock,data_bus,r0_out);
registrador r1(regs_enable[1],clock,data_bus,r1_out);
registrador r2(regs_enable[2],clock,data_bus,r2_out);
registrador r3(regs_enable[3],clock,data_bus,r3_out);
registrador r4(regs_enable[4],clock,data_bus,r4_out);
registrador r5(regs_enable[5],clock,data_bus,r5_out);
registrador r6(regs_enable[6],clock,data_bus,r6_out);
registrador r7(regs_enable[7],clock,data_bus,r7_out);
registrador a(a_reg_enable,clock,data_bus,a_reg_out);
registrador r(alu_reg_enable,clock,data_bus,alu_out);

assign bus = data_bus;

endmodule;

Fonte/testbench.v
`include "processador.v"
module testbench;

reg clock = 0;
reg resetn = 1;
reg  [15:0] iin;
wire [15:0] bus;

always #1 clock = !clock;

initial $dumpfile("testbench.vcd");
initial $dumpvars(0,testbench);

processador p(clock, resetn, iin, bus);

initial begin
    # 0 resetn <= 1'b0;
    # 0 iin =  16'b1010000000011100;
    # 8 iin =  16'b1010010000001010;
    # 8 iin =  16'b0010000010000000;
    # 8 iin =  16'b1000010000000000;
    # 8 $finish;
end
endmodule

Fonte/testbench.vcd
$date
	Sat Jun  7 15:52:00 2025
$end
$version
	Icarus Verilog
$end
$timescale
	1s
$end
$scope module testbench $end
$var wire 16 ! bus [15:0] $end
$var reg 1 " clock $end
$var reg 16 # iin [15:0] $end
$var reg 1 $ resetn $end
$scope module p $end
$var wire 16 % bus [15:0] $end
$var wire 1 " clock $end
$var wire 16 & iin [15:0] $end
$var wire 1 $ resetn $end
$var wire 2 ' saida_contador [1:0] $end
$var wire 8 ( regs_enable [7:0] $end
$var wire 16 ) r7_out [15:0] $end
$var wire 16 * r6_out [15:0] $end
$var wire 16 + r5_out [15:0] $end
$var wire 16 , r4_out [15:0] $end
$var wire 16 - r3_out [15:0] $end
$var wire 16 . r2_out [15:0] $end
$var wire 16 / r1_out [15:0] $end
$var wire 16 0 r0_out [15:0] $end
$var wire 4 1 mux_select [3:0] $end
$var wire 16 2 imm [15:0] $end
$var wire 16 3 data_bus [15:0] $end
$var wire 1 4 clear $end
$var wire 1 5 alu_reg_enable $end
$var wire 16 6 alu_out [15:0] $end
$var wire 2 7 alu_op_select [1:0] $end
$var wire 16 8 a_reg_out [15:0] $end
$var wire 1 9 a_reg_enable $end
$scope module a $end
$var wire 1 " clock $end
$var wire 1 9 wr_enable $end
$var wire 16 : entrada_reg [15:0] $end
$var reg 16 ; saida_reg [15:0] $end
$upscope $end
$scope module cont $end
$var wire 1 " clock $end
$var wire 1 4 clear $end
$var reg 2 < saida_cont [1:0] $end
$upscope $end
$scope module ext $end
$var wire 10 = iin [9:0] $end
$var wire 16 > imediato [15:0] $end
$upscope $end
$scope module log_ctl $end
$var wire 1 9 a_reg_enable $end
$var wire 1 5 alu_reg_enable $end
$var wire 2 ? counter [1:0] $end
$var wire 9 @ iin [8:0] $end
$var wire 1 $ resetn $end
$var wire 8 A regs_select [7:0] $end
$var wire 8 B regs_enable [7:0] $end
$var wire 2 C alu_op_select [1:0] $end
$var reg 1 4 clear $end
$var reg 4 D mux_select [3:0] $end
$var reg 3 E opcode [2:0] $end
$var reg 3 F rx [2:0] $end
$var reg 3 G ry [2:0] $end
$scope module decode $end
$var wire 3 H chave [2:0] $end
$var reg 8 I saida [7:0] $end
$upscope $end
$upscope $end
$scope module mux $end
$var wire 16 J immediate [15:0] $end
$var wire 4 K select [3:0] $end
$var wire 16 L r7 [15:0] $end
$var wire 16 M r6 [15:0] $end
$var wire 16 N r5 [15:0] $end
$var wire 16 O r4 [15:0] $end
$var wire 16 P r3 [15:0] $end
$var wire 16 Q r2 [15:0] $end
$var wire 16 R r1 [15:0] $end
$var wire 16 S r0 [15:0] $end
$var wire 16 T r [15:0] $end
$var reg 16 U saida [15:0] $end
$upscope $end
$scope module r $end
$var wire 1 " clock $end
$var wire 16 V entrada_reg [15:0] $end
$var wire 1 5 wr_enable $end
$var reg 16 W saida_reg [15:0] $end
$upscope $end
$scope module r0 $end
$var wire 1 " clock $end
$var wire 16 X entrada_reg [15:0] $end
$var wire 1 Y wr_enable $end
$var reg 16 Z saida_reg [15:0] $end
$upscope $end
$scope module r1 $end
$var wire 1 " clock $end
$var wire 16 [ entrada_reg [15:0] $end
$var wire 1 \ wr_enable $end
$var reg 16 ] saida_reg [15:0] $end
$upscope $end
$scope module r2 $end
$var wire 1 " clock $end
$var wire 16 ^ entrada_reg [15:0] $end
$var wire 1 _ wr_enable $end
$var reg 16 ` saida_reg [15:0] $end
$upscope $end
$scope module r3 $end
$var wire 1 " clock $end
$var wire 16 a entrada_reg [15:0] $end
$var wire 1 b wr_enable $end
$var reg 16 c saida_reg [15:0] $end
$upscope $end
$scope module r4 $end
$var wire 1 " clock $end
$var wire 16 d entrada_reg [15:0] $end
$var wire 1 e wr_enable $end
$var reg 16 f saida_reg [15:0] $end
$upscope $end
$scope module r5 $end
$var wire 1 " clock $end
$var wire 16 g entrada_reg [15:0] $end
$var wire 1 h wr_enable $end
$var reg 16 i saida_reg [15:0] $end
$upscope $end
$scope module r6 $end
$var wire 1 " clock $end
$var wire 16 j entrada_reg [15:0] $end
$var wire 1 k wr_enable $end
$var reg 16 l saida_reg [15:0] $end
$upscope $end
$scope module r7 $end
$var wire 1 " clock $end
$var wire 16 m entrada_reg [15:0] $end
$var wire 1 n wr_enable $end
$var reg 16 o saida_reg [15:0] $end
$upscope $end
$upscope $end
$upscope $end
$enddefinitions $end
$comment Show the parameter values. $end
$dumpall
$end
#0
$dumpvars
bx o
0n
bz m
bx l
0k
bz j
bx i
0h
bz g
bx f
0e
bz d
bx c
0b
bz a
bx `
0_
bz ^
bx ]
0\
bz [
bx Z
0Y
bz X
bx W
bz V
bz U
bx T
bx S
bx R
bx Q
bx P
bx O
bx N
bx M
bx L
b1111 K
b11100 J
bx I
bx H
bx G
bx F
bx E
b1111 D
bx C
b0 B
bx A
b101000000 @
b0 ?
b11100 >
b11100 =
b0 <
bx ;
bz :
09
bx 8
bx 7
bx 6
05
04
bz 3
b11100 2
b1111 1
bx 0
bx /
bx .
bx -
bx ,
bx +
bx *
bx )
b0 (
b0 '
b1010000000011100 &
bz %
0$
b1010000000011100 #
0"
bz !
$end
#1
b11 7
b11 C
b1 A
b1 I
b0 G
b0 F
b0 H
b101 E
09
b1 '
b1 <
b1 ?
1"
#2
0"
#3
b10 '
b10 <
b10 ?
1"
#4
0"
#5
b11100 !
b11100 %
b11100 3
b11100 :
b11100 U
b11100 V
b11100 X
b11100 [
b11100 ^
b11100 a
b11100 d
b11100 g
b11100 j
b11100 m
b1000 1
b1000 D
b1000 K
1Y
b1 (
b1 B
b11 '
b11 <
b11 ?
1"
#6
0"
#7
bz !
bz %
bz 3
bz :
bz U
bz V
bz X
bz [
bz ^
bz a
bz d
bz g
bz j
bz m
b1111 1
b1111 D
b1111 K
0Y
b0 (
b0 B
b11100 0
b11100 S
b11100 Z
b0 '
b0 <
b0 ?
1"
#8
b1010 2
b1010 >
b1010 J
b1010 =
b101001000 @
0"
b1010010000001010 #
b1010010000001010 &
#9
b10 A
b10 I
b1 F
b1 H
b1 '
b1 <
b1 ?
1"
#10
0"
#11
b10 '
b10 <
b10 ?
1"
#12
0"
#13
b1010 !
b1010 %
b1010 3
b1010 :
b1010 U
b1010 V
b1010 X
b1010 [
b1010 ^
b1010 a
b1010 d
b1010 g
b1010 j
b1010 m
b1000 1
b1000 D
b1000 K
1\
b10 (
b10 B
b11 '
b11 <
b11 ?
1"
#14
0"
#15
bz !
bz %
bz 3
bz :
bz U
bz V
bz X
bz [
bz ^
bz a
bz d
bz g
bz j
bz m
b1111 1
b1111 D
b1111 K
0\
b0 (
b0 B
b1010 /
b1010 R
b1010 ]
b0 '
b0 <
b0 ?
1"
#16
b10000000 2
b10000000 >
b10000000 J
b10000000 =
b1000001 @
0"
b10000010000000 #
b10000010000000 &
#17
b11100 !
b11100 %
b11100 3
b11100 :
b11100 U
b11100 V
b11100 X
b11100 [
b11100 ^
b11100 a
b11100 d
b11100 g
b11100 j
b11100 m
b0 1
b0 D
b0 K
19
b1 7
b1 C
b1 A
b1 I
b1 G
b0 F
b0 H
b1 E
b1 '
b1 <
b1 ?
1"
#18
0"
#19
b1010 !
b1010 %
b1010 3
b1010 :
b1010 U
b1010 V
b1010 X
b1010 [
b1010 ^
b1010 a
b1010 d
b1010 g
b1010 j
b1010 m
b1 1
b1 D
b1 K
09
15
b11100 8
b11100 ;
b10 '
b10 <
b10 ?
1"
#20
0"
#21
b1001 1
b1001 D
b1001 K
1Y
b1 (
b1 B
05
b11 '
b11 <
b11 ?
b1010 6
b1010 T
b1010 W
1"
#22
0"
#23
bz !
bz %
bz 3
bz :
bz U
bz V
bz X
bz [
bz ^
bz a
bz d
bz g
bz j
bz m
b1111 1
b1111 D
b1111 K
0Y
b0 (
b0 B
b1010 0
b1010 S
b1010 Z
b0 '
b0 <
b0 ?
1"
#24
b0 2
b0 >
b0 J
b0 =
b100001000 @
0"
b1000010000000000 #
b1000010000000000 &
#25
b11 7
b11 C
b10 A
b10 I
b0 G
b1 F
b1 H
b100 E
09
b1 '
b1 <
b1 ?
1"
#26
0"
#27
b10 '
b10 <
b10 ?
1"
#28
0"
#29
b1010 !
b1010 %
b1010 3
b1010 :
b1010 U
b1010 V
b1010 X
b1010 [
b1010 ^
b1010 a
b1010 d
b1010 g
b1010 j
b1010 m
b1 1
b1 D
b1 K
b11 '
b11 <
b11 ?
1"
#30
0"
#31
bz !
bz %
bz 3
bz :
bz U
bz V
bz X
bz [
bz ^
bz a
bz d
bz g
bz j
bz m
b1111 1
b1111 D
b1111 K
b0 '
b0 <
b0 ?
1"
