Fonte/registrador.v
module registrador(wr_enable,clock,entrada_reg,saida_reg);

input wr_enable;
input clock;
input [15:0] entrada_reg;
output reg [15:0] saida_reg;

always @(posedge clock)
begin
    if(wr_enable)
        saida_reg <= entrada_reg;
end

endmodule

Fonte/decodificador.v
module decodificador(
    input      [2:0] chave,
    output reg [7:0] saida
);

always @(chave) begin
    saida        = 8'h00;
    saida[chave] = 1'b1;
end

endmodule

Fonte/logica_de_controle.v
`include "decodificador.v"

module logica_de_controle(
    input        resetn,
    input  [1:0] counter,
    input  [8:0] iin,
    output [2:0] reg_address,
    output [7:0] regs_enable,
    output [1:0] alu_op_select,
    output       reg_a_enable,
    output       imm_select,
    output       alu_reg_enable,
    output       alu_reg_select,
    output  reg  clear
);

`define REP 3'b111
`define LDI 3'b101
`define OUT 3'b100

reg  [2:0] opcode, rx, ry;
wire [7:0] regs_select;
decodificador decode(rx, regs_select);

assign reg_a_enable   = (counter == 2'b01); 
assign reg_address    = (counter == 2'b01 || opcode == `OUT) ? {1'b0, rx} : {1'b0, ry};
assign alu_reg_enable = (counter == 2'b10);
assign alu_reg_select = (counter == 2'b11 && !opcode[2]);
assign imm_select     = (counter == 2'b11 && opcode == `LDI);
assign regs_enable    = (counter == 2'b11 && opcode != `OUT) ? regs_select : 8'h00;
assign alu_op_select  = (!opcode[2]) ? opcode[1:0] : 2'b11;

always @(counter) 
begin
    if(counter == 2'b01) begin
        opcode <= iin[8:6];
        rx     <= iin[5:3];
        ry     <= iin[2:0];
    end
end

always @(negedge resetn)
begin
    clear = 1'b1;
    clear = 1'b0;
end

endmodule

Fonte/extensor.v
module extensor(
    input  [9:0] iin,
    output [15:0] imediato
);

assign imediato[9:0] = iin;
assign imediato[15:10] = {6{iin[9]}};

endmodule;

Fonte/contador.v
module contador(
    input clock,
    input clear,
    output reg [1:0] saida_cont);

always @(clear)
begin
    saida_cont <= 2'b00;
end

always @(posedge clock)
begin
    saida_cont <= saida_cont + 2'b01;
end

endmodule

Fonte/processador.v
`include "registrador.v"
`include "logica_de_controle.v"
`include "contador.v"
`include "extensor.v"

module processador(
    input clock,
    input resetn,
    input  [15:0] iin,
    output [15:0] bus
);

wire [2:0] reg_address;
wire [7:0] regs_enable;
wire [1:0] alu_op_select;
wire [1:0] saida_contador;
wire [15:0] data_bus, imm, reg_a_out, alu_out;
wire [15:0] r0_out, r1_out, r2_out, r3_out, r4_out, r5_out, r6_out, r7_out;

contador cont(clock, clear, saida_contador);
extensor ext(iin[9:0], imm);
logica_de_controle log_ctl(resetn, saida_contador, iin[15:7],
    reg_address, regs_enable, alu_op_select, reg_a_enable, imm_select,
    alu_output_enable, alu_output_select, clear);

registrador r0(regs_enable[0],clock,data_bus,r0_out);
registrador r1(regs_enable[1],clock,data_bus,r1_out);
registrador r2(regs_enable[2],clock,data_bus,r2_out);
registrador r3(regs_enable[3],clock,data_bus,r3_out);
registrador r4(regs_enable[4],clock,data_bus,r4_out);
registrador r5(regs_enable[5],clock,data_bus,r5_out);
registrador r6(regs_enable[6],clock,data_bus,r6_out);
registrador r7(regs_enable[7],clock,data_bus,r7_out);
registrador a(reg_a_enable,clock,data_bus,reg_a_out);
registrador r(alu_output_enable,clock,data_bus,alu_out);

assign bus = data_bus;

endmodule;

Fonte/testbench.v
`include "processador.v"
module testbench;

reg clock = 0;
reg resetn = 1;
reg  [15:0] iin;
wire [15:0] bus;

always #1 clock = !clock;

initial $dumpfile("testbench.vcd");
initial $dumpvars(0,testbench);

processador p(clock, resetn, iin, bus);

initial begin
    # 0 resetn <= 1'b0;
    # 0 iin <= 16'b1010000000011100;
    # 8 iin = 16'b1010010000001010;
    # 8 iin = 16'b1000000000000000;
    # 8 $finish;
end
endmodule

Fonte/testbench.vcd
$date
	Sat Jun  7 11:01:44 2025
$end
$version
	Icarus Verilog
$end
$timescale
	1s
$end
$scope module testbench $end
$var wire 16 ! bus [15:0] $end
$var reg 1 " clock $end
$var reg 16 # iin [15:0] $end
$var reg 1 $ resetn $end
$scope module p $end
$var wire 16 % bus [15:0] $end
$var wire 1 " clock $end
$var wire 16 & data_bus [15:0] $end
$var wire 16 ' iin [15:0] $end
$var wire 1 $ resetn $end
$var wire 2 ( saida_contador [1:0] $end
$var wire 8 ) regs_enable [7:0] $end
$var wire 3 * reg_address [2:0] $end
$var wire 16 + reg_a_out [15:0] $end
$var wire 1 , reg_a_enable $end
$var wire 16 - r7_out [15:0] $end
$var wire 16 . r6_out [15:0] $end
$var wire 16 / r5_out [15:0] $end
$var wire 16 0 r4_out [15:0] $end
$var wire 16 1 r3_out [15:0] $end
$var wire 16 2 r2_out [15:0] $end
$var wire 16 3 r1_out [15:0] $end
$var wire 16 4 r0_out [15:0] $end
$var wire 1 5 imm_select $end
$var wire 16 6 imm [15:0] $end
$var wire 1 7 clear $end
$var wire 1 8 alu_output_select $end
$var wire 1 9 alu_output_enable $end
$var wire 16 : alu_out [15:0] $end
$var wire 2 ; alu_op_select [1:0] $end
$scope module a $end
$var wire 1 " clock $end
$var wire 16 < entrada_reg [15:0] $end
$var wire 1 , wr_enable $end
$var reg 16 = saida_reg [15:0] $end
$upscope $end
$scope module cont $end
$var wire 1 " clock $end
$var wire 1 7 clear $end
$var reg 2 > saida_cont [1:0] $end
$upscope $end
$scope module ext $end
$var wire 10 ? iin [9:0] $end
$var wire 16 @ imediato [15:0] $end
$upscope $end
$scope module log_ctl $end
$var wire 1 8 alu_reg_select $end
$var wire 2 A counter [1:0] $end
$var wire 9 B iin [8:0] $end
$var wire 1 5 imm_select $end
$var wire 1 $ resetn $end
$var wire 8 C regs_select [7:0] $end
$var wire 8 D regs_enable [7:0] $end
$var wire 3 E reg_address [2:0] $end
$var wire 1 , reg_a_enable $end
$var wire 1 9 alu_reg_enable $end
$var wire 2 F alu_op_select [1:0] $end
$var reg 1 7 clear $end
$var reg 3 G opcode [2:0] $end
$var reg 3 H rx [2:0] $end
$var reg 3 I ry [2:0] $end
$scope module decode $end
$var wire 3 J chave [2:0] $end
$var reg 8 K saida [7:0] $end
$upscope $end
$upscope $end
$scope module r $end
$var wire 1 " clock $end
$var wire 16 L entrada_reg [15:0] $end
$var wire 1 9 wr_enable $end
$var reg 16 M saida_reg [15:0] $end
$upscope $end
$scope module r0 $end
$var wire 1 " clock $end
$var wire 16 N entrada_reg [15:0] $end
$var wire 1 O wr_enable $end
$var reg 16 P saida_reg [15:0] $end
$upscope $end
$scope module r1 $end
$var wire 1 " clock $end
$var wire 16 Q entrada_reg [15:0] $end
$var wire 1 R wr_enable $end
$var reg 16 S saida_reg [15:0] $end
$upscope $end
$scope module r2 $end
$var wire 1 " clock $end
$var wire 16 T entrada_reg [15:0] $end
$var wire 1 U wr_enable $end
$var reg 16 V saida_reg [15:0] $end
$upscope $end
$scope module r3 $end
$var wire 1 " clock $end
$var wire 16 W entrada_reg [15:0] $end
$var wire 1 X wr_enable $end
$var reg 16 Y saida_reg [15:0] $end
$upscope $end
$scope module r4 $end
$var wire 1 " clock $end
$var wire 16 Z entrada_reg [15:0] $end
$var wire 1 [ wr_enable $end
$var reg 16 \ saida_reg [15:0] $end
$upscope $end
$scope module r5 $end
$var wire 1 " clock $end
$var wire 16 ] entrada_reg [15:0] $end
$var wire 1 ^ wr_enable $end
$var reg 16 _ saida_reg [15:0] $end
$upscope $end
$scope module r6 $end
$var wire 1 " clock $end
$var wire 16 ` entrada_reg [15:0] $end
$var wire 1 a wr_enable $end
$var reg 16 b saida_reg [15:0] $end
$upscope $end
$scope module r7 $end
$var wire 1 " clock $end
$var wire 16 c entrada_reg [15:0] $end
$var wire 1 d wr_enable $end
$var reg 16 e saida_reg [15:0] $end
$upscope $end
$upscope $end
$upscope $end
$enddefinitions $end
$comment Show the parameter values. $end
$dumpall
$end
#0
$dumpvars
bx e
0d
bz c
bx b
0a
bz `
bx _
0^
bz ]
bx \
0[
bz Z
bx Y
0X
bz W
bx V
0U
bz T
bx S
0R
bz Q
bx P
0O
bz N
bx M
bz L
bx K
bx J
bx I
bx H
bx G
bx F
bx E
b0 D
bx C
b101000000 B
b0 A
b11100 @
b11100 ?
b0 >
bx =
bz <
bx ;
bx :
09
08
07
b11100 6
05
bx 4
bx 3
bx 2
bx 1
bx 0
bx /
bx .
bx -
0,
bx +
bx *
b0 )
b0 (
b1010000000011100 '
bz &
bz %
0$
b1010000000011100 #
0"
bz !
$end
#1
b0 *
b0 E
b11 ;
b11 F
b1 C
b1 K
b0 I
b0 H
b0 J
b101 G
1,
b1 (
b1 >
b1 A
1"
#2
0"
#3
bz +
bz =
0,
19
b10 (
b10 >
b10 A
1"
#4
0"
#5
1O
b1 )
b1 D
15
09
b11 (
b11 >
b11 A
bz :
bz M
1"
#6
0"
#7
0O
b0 )
b0 D
05
bz 4
bz P
b0 (
b0 >
b0 A
1"
#8
b1010 6
b1010 @
b1010 ?
b101001000 B
0"
b1010010000001010 #
b1010010000001010 '
#9
b1 *
b1 E
b10 C
b10 K
b1 H
b1 J
1,
b1 (
b1 >
b1 A
1"
#10
0"
#11
b0 *
b0 E
0,
19
b10 (
b10 >
b10 A
1"
#12
0"
#13
1R
b10 )
b10 D
15
09
b11 (
b11 >
b11 A
1"
#14
0"
#15
0R
b0 )
b0 D
05
bz 3
bz S
b0 (
b0 >
b0 A
1"
#16
b0 6
b0 @
b0 ?
b100000000 B
0"
b1000000000000000 #
b1000000000000000 '
#17
b1 C
b1 K
b0 H
b0 J
b100 G
b0 *
b0 E
1,
b1 (
b1 >
b1 A
1"
#18
0"
#19
0,
19
b10 (
b10 >
b10 A
1"
#20
0"
#21
09
b11 (
b11 >
b11 A
1"
#22
0"
#23
b0 (
b0 >
b0 A
1"
